chile_rut/__init__.py
chile_rut/chile_rut.py
chile_rut/validator_test.py
chile_rut-1.1.dist-info/METADATA
chile_rut-1.1.dist-info/RECORD
chile_rut-1.1.dist-info/WHEEL
chile_rut-1.1.dist-info/top_level.txt
