Metadata-Version: 2.1
Name: chile-rut
Version: 1.1
Summary: Validator and generator of Chile id
Home-page: https://github.com/gmgarciag/chile_rut
Author: Gonzalo Garcia
Author-email: gmgarcia@uc.cl
License: MIT
Platform: UNKNOWN
